LICENSE
MANIFEST.in
README.md
setup.py
./src/pcapml/src/util.cpp
./src/pcapml/src/pcapng/block_pcapng.cpp
./src/pcapml/src/pcapng/reader_pcapng.cpp
./src/pcapml/src/pcapng/sorter_pcapng.cpp
./src/pcapml/src/sample/sample.cpp
./src/pcapml/src/sample/sampler.cpp
./src/sampler/pcapml_fe_sampler.cpp
src/pcapml/include/util.hpp
src/pcapml/include/dir/dir.hpp
src/pcapml/include/label/label.hpp
src/pcapml/include/label/labeler.hpp
src/pcapml/include/pcap/reader_pcap.hpp
src/pcapml/include/pcap/writer_pcap.hpp
src/pcapml/include/pcapng/block_pcapng.hpp
src/pcapml/include/pcapng/reader_pcapng.hpp
src/pcapml/include/pcapng/sorter_pcapng.hpp
src/pcapml/include/pcapng/splitter_pcapng.hpp
src/pcapml/include/pcapng/writer_pcapng.hpp
src/pcapml/include/sample/sample.hpp
src/pcapml/include/sample/sampler.hpp
src/pcapml_fe.egg-info/PKG-INFO
src/pcapml_fe.egg-info/SOURCES.txt
src/pcapml_fe.egg-info/dependency_links.txt
src/pcapml_fe.egg-info/requires.txt
src/pcapml_fe.egg-info/top_level.txt
src/pcapml_fe_helpers/__init__.py
src/pcapml_fe_helpers/helpers.py